{
  "key": "10159",
  "title": "RigVeda Hymn 10159",
  "orig": "<HTML>\n<HEAD>\n<link rel=\"stylesheet\" type=\"text/css\" href=\"../../css/marg.css\">\n<META HTTP-EQUIV=\"Content-Type\" CONTENT=\"text/html; charset=UTF-8\">\n<META name=\"description\" content=\"Rig Veda, tr. by Ralph T.H. Griffith, [1896], full text etext at sacred-texts.com\">\n<META name=\"keywords\" content=\"Rig Veda Hinduism Vedic Rik\">\n<TITLE>Rig Veda: Rig-Veda, Book 10: HYMN CLIX. Saci Paulomi.</TITLE>\n</HEAD>\n<BODY>\n<CENTER>\n<A HREF=\"../../cdshop/index.htm\"><IMG SRC=\"../../cdshop/cdinfo.jpg\" BORDER=\"0\"></A><BR>\n<A HREF=\"../../index.htm\">Sacred Texts</A>&nbsp;\n<A HREF=\"../index.htm\">Hinduism</A>&nbsp;\n<A HREF=\"index.htm\">Index</A>&nbsp;\n\n<BR>\n<A HREF=\"../rvsan/rv10159.htm\">Sanskrit</A>&nbsp;\n\n<BR>\n<BR><A HREF=\"rvi10.htm\">Rig-Veda, Book 10 Index</A><BR>\n&nbsp;\n<A HREF=\"rv10158.htm\">Previous</A>&nbsp;\n<A HREF=\"rv10160.htm\">Next</A>&nbsp;\n<HR><A HREF=\"http://www.amazon.com/exec/obidos/ASIN/B001VEIA6U/internetsacredte\">Buy this Book at Amazon.com</A></CENTER>\n<HR>\n<P ALIGN=\"CENTER\"><FONT SIZE=\"-1\" COLOR=\"GREEN\"><I>Rig Veda</I>, tr. by Ralph T.H. Griffith, [1896], at sacred-texts.com</FONT></P><HR></p>  <h3 align=\"center\" align=\"center\">HYMN CLIX. Saci Paulomi.</h3>  \n<p>1. YON Sun hath mounted up, and this my happy fate hate mounted high.<br> I knowing this, as conqueror have won my husband for mine own.<br> 2 I am the banner and the head, a mighty arbitress am I:<br> I am victorious, and my Lord shall be submissive to my will.<br> 3 My Sons are slayers of the foe, my Daughter is a ruling Queen:<br> I am victorious: o&#146;er my Lord my song of triumph is supreme.<br> 4 Oblation, that which Indra gave and thus grew glorious and most high,&#151;<br> This have I offered, O ye Gods, and rid me of each rival wife.<br> 5 Destroyer of the rival wife, Sole Spouse, victorious, conqueror,<br> The others' glory have I seized as &#146;twere the wealth of weaker Dames.<br> 6 I have subdued as conqueror these rivals, these my fellow-wives,<br> That I may hold imperial sway over this Hero and the folk.</p>  \n<p><HR>\n<CENTER>\n<A HREF=\"rv10160.htm\">Next: HYMN CLX. Indra.</A></CENTER>\n</BODY>\n</HTML>\n",
  "link": "hymns/10159.html",
  "api": "json/hymns/10159.json",
  "data": {
    "key": "10159",
    "title": "HYMN CLIX. Saci Paulomi.",
    "describe": "YON Sun hath mounted up, and this my happy fate hate mounted high.",
    "feecting": "p:YON Sun hath mounted up, and this my happy fate hate mounted high.\np: I knowing this, as conqueror have won my husband for mine own.\r\np:I am the banner and the head, a mighty arbitress am I: I am victorious, and my Lord shall be submissive to my will.\np:My Sons are slayers of the foe, my Daughter is a ruling Queen: I am victorious: o’er my Lord my song of triumph is supreme.\np:Oblation, that which Indra gave and thus grew glorious and most high. This have I offered, O ye Devas, and rid me of each rival wife.\np:Destroyer of the rival wife, Sole Spouse, victorious, conqueror, the others' glory have I seized as ’twere the wealth of weaker Dames.\np:I have subdued as conqueror these rivals, these my fellow-wives, that . May hold imperial sway over this Hero and the folk.",
    "meta": {
      "next": "10160",
      "previous": "10158",
      "book": "10",
      "original": "https://sacred-texts.com/hin/rigveda/rv10159.htm",
      "sanskrit": "https://sacred-texts.com/hin/rvsan/rv10159.htm"
    },
    "deities": [
      {
        "name": "O ye ",
        "hymns": [
          {
            "key": "10159",
            "title": "HYMN CLIX. Saci Paulomi."
          }
        ]
      }
    ]
  },
  "created": 1638558279826,
  "updated": 1667450405419
}